cython_package_example-0.1.6.dist-info/RECORD
cython_package_example-0.1.6.dist-info/top_level.txt
cython_package_example-0.1.6.dist-info/WHEEL
cython_package_example-0.1.6.dist-info/METADATA
cython_package_example-0.1.6.dist-info/LICENSE.txt
cypack/utils.pxd
cypack/utils.cpython-310-x86_64-linux-gnu.so
cypack/fibonacci.cpython-310-x86_64-linux-gnu.so
cypack/answer.cpython-310-x86_64-linux-gnu.so
cypack/__init__.py
cypack/sub/wrong.cpython-310-x86_64-linux-gnu.so
cypack/sub/helper.pxd
cypack/sub/helper.h
cypack/sub/__init__.py
cypack/data/zen.txt
